{
  "sources": [
    {
      "idioma": "Subtitulado Descarga 1DM",
      "url": "https://streamwish.top/e/gn7tq3l0ik2x"
    },
    {
      "idioma": "Prueba 2DM",
      "url": "https://emturbovid.com/t/iZ3VMau8j1vRJvom4c8c"
    },
    {
      "idioma": "Prueba Plus",
      "url": "https://vidhideplus.com/v/7l1od4t0hvqp"
    },
    {
      "idioma": "Prueba VI",
      "url": "https://ok.ru/video/9912347396716"
    },
    {
      "idioma": "Prueba Oka 1DM",
      "url": "https://ok.ru/video/1321731426889"
    }
  ]
}
